PySkyPlusHD/__init__.py
PySkyPlusHD/buttons.py
PySkyPlusHD-0.2.0.dist-info/LICENSE
PySkyPlusHD-0.2.0.dist-info/METADATA
PySkyPlusHD-0.2.0.dist-info/WHEEL
PySkyPlusHD-0.2.0.dist-info/top_level.txt
PySkyPlusHD-0.2.0.dist-info/RECORD
