Metadata-Version: 2.1
Name: PySkyPlusHD
Version: 0.2.0
Summary: Python package to control a Sky+ HD box
Home-page: https://github.com/GreenTurtwig/PySkyPlusHD
Author: GreenTurtwig
License: UNKNOWN
Platform: UNKNOWN
Classifier: Programming Language :: Python :: 3
Classifier: License :: OSI Approved :: Apache Software License 
Classifier: Operating System :: OS Independent
Classifier: Topic :: Home Automation
Requires-Python: >=3.6
